cppbuiltins.cpython-37m-x86_64-linux-gnu.so
cppbuiltins-0.5.0.dist-info/WHEEL
cppbuiltins-0.5.0.dist-info/top_level.txt
cppbuiltins-0.5.0.dist-info/METADATA
cppbuiltins-0.5.0.dist-info/LICENSE
cppbuiltins-0.5.0.dist-info/RECORD
