Metadata-Version: 2.1
Name: cppbuiltins
Version: 0.5.0
Summary: Alternative implementation of python builtins based on C++ `std` library.
Home-page: https://github.com/lycantropos/cppbuiltins/
Author: Azat Ibrakov
Author-email: azatibrakov@gmail.com
License: MIT License
Download-URL: https://github.com/lycantropos/cppbuiltins/archive/master.zip
Platform: UNKNOWN
Classifier: License :: OSI Approved :: MIT License
Classifier: Programming Language :: Python :: 3.5
Classifier: Programming Language :: Python :: 3.6
Classifier: Programming Language :: Python :: 3.7
Classifier: Programming Language :: Python :: 3.8
Classifier: Programming Language :: Python :: 3.9
Classifier: Programming Language :: Python :: Implementation :: CPython
Requires-Python: >=3.5
License-File: LICENSE
